README.md
setup.py
Pix_Chan/__init__.py
Pix_Chan/main.py
Pix_Chan.egg-info/PKG-INFO
Pix_Chan.egg-info/SOURCES.txt
Pix_Chan.egg-info/dependency_links.txt
Pix_Chan.egg-info/requires.txt
Pix_Chan.egg-info/top_level.txt