Metadata-Version: 2.1
Name: Pix-Chan
Version: 1.0.1
Summary: An API wrapper for the PixAI
Home-page: https://github.com/taka-4602/Pix-Chan
Author: taka4602
Author-email: taka4602@gmail.com
Keywords: pixai
Classifier: Programming Language :: Python :: 3
Classifier: License :: OSI Approved :: MIT License
Classifier: Operating System :: OS Independent
Requires-Python: >=3.6
Requires-Dist: requests
